macrocorr/__init__.py
macrocorr/correlator.py
macrocorr/macroIndicator.py
macrocorr/utils.py
macrocorr-0.1.6.dist-info/LICENSE.txt
macrocorr-0.1.6.dist-info/METADATA
macrocorr-0.1.6.dist-info/WHEEL
macrocorr-0.1.6.dist-info/top_level.txt
macrocorr-0.1.6.dist-info/RECORD
