Metadata-Version: 2.1
Name: macrocorr
Version: 0.1.6
Summary: a Python package for analyzing the correlation between macroeconomic indicators and time-series data
Author-email: Seoli Kim <seolikim1225@gmail.com>
License: Copyright (c) 2023 Seoli Kim
Project-URL: Homepage, https://github.com/SeoliKim/macrocorr
Keywords: economics,correlation,time-series
Classifier: Development Status :: 3 - Alpha
Classifier: Intended Audience :: Science/Research
Classifier: Topic :: Office/Business :: Financial
Classifier: Natural Language :: English
Classifier: License :: OSI Approved :: MIT License
Classifier: Programming Language :: Python :: 3
Classifier: Programming Language :: Python :: 3
Classifier: Programming Language :: Python :: 3.7
Classifier: Programming Language :: Python :: 3.8
Classifier: Programming Language :: Python :: 3.9
Classifier: Programming Language :: Python :: 3.10
Classifier: Programming Language :: Python :: 3.11
Classifier: Programming Language :: Python :: 3 :: Only
Requires-Python: >=3.7
License-File: LICENSE.txt
Requires-Dist: numpy >=1.23.5
Requires-Dist: pandas >=1.5.2
Requires-Dist: matplotlib >=3.7.2
Requires-Dist: scipy >=1.11.1
Requires-Dist: yfinance >=0.2.26
Requires-Dist: wbgapi >=1.0.12
Requires-Dist: wheel
